pobo/__init__.py
pobo/client.py
pobo/enums.py
pobo/exceptions.py
pobo/webhook_handler.py
pobo/dto/__init__.py
pobo/dto/blog.py
pobo/dto/category.py
pobo/dto/content.py
pobo/dto/import_result.py
pobo/dto/localized_string.py
pobo/dto/paginated_response.py
pobo/dto/parameter.py
pobo/dto/product.py
pobo/dto/webhook_payload.py
pobo_sdk-1.0.5.dist-info/METADATA
pobo_sdk-1.0.5.dist-info/WHEEL
pobo_sdk-1.0.5.dist-info/licenses/LICENSE
pobo_sdk-1.0.5.dist-info/RECORD
