Metadata-Version: 2.4
Name: pobo-sdk
Version: 1.0.5
Summary: Official Python SDK for Pobo API V2 - product content management and webhooks
Project-URL: Homepage, https://github.com/pobo-builder/python-sdk
Project-URL: Documentation, https://github.com/pobo-builder/python-sdk#readme
Project-URL: Repository, https://github.com/pobo-builder/python-sdk
Project-URL: Issues, https://github.com/pobo-builder/python-sdk/issues
Author-email: Pobo <tomas@pobo.cz>
License-Expression: MIT
License-File: LICENSE
Keywords: api,ecommerce,pobo,product-content,sdk
Classifier: Development Status :: 5 - Production/Stable
Classifier: Intended Audience :: Developers
Classifier: License :: OSI Approved :: MIT License
Classifier: Operating System :: OS Independent
Classifier: Programming Language :: Python :: 3
Classifier: Programming Language :: Python :: 3.9
Classifier: Programming Language :: Python :: 3.10
Classifier: Programming Language :: Python :: 3.11
Classifier: Programming Language :: Python :: 3.12
Classifier: Programming Language :: Python :: 3.13
Classifier: Topic :: Software Development :: Libraries :: Python Modules
Requires-Python: >=3.9
Requires-Dist: pydantic>=2.0.0
Requires-Dist: requests>=2.28.0
Provides-Extra: dev
Requires-Dist: mypy>=1.0.0; extra == 'dev'
Requires-Dist: pytest-cov>=4.0.0; extra == 'dev'
Requires-Dist: pytest>=7.0.0; extra == 'dev'
Requires-Dist: responses>=0.23.0; extra == 'dev'
Requires-Dist: ruff>=0.1.0; extra == 'dev'
Requires-Dist: types-requests>=2.28.0; extra == 'dev'
